Metadata-Version: 2.1
Name: feast-doris
Version: 0.1.2
Summary: Python SDK for Feast
Home-page: https://github.com/feast-dev/feast
Author: DQLabs
License: Apache
Classifier: License :: OSI Approved :: Apache Software License
Classifier: Programming Language :: Python
Classifier: Programming Language :: Python :: 3
Classifier: Programming Language :: Python :: 3.9
Requires-Python: >=3.9.0
License-File: LICENSE
Requires-Dist: click <9.0.0,>=7.0.0
Requires-Dist: colorama <1,>=0.3.9
Requires-Dist: dill ~=0.3.0
Requires-Dist: mypy-protobuf >=3.1
Requires-Dist: Jinja2 <4,>=2
Requires-Dist: jsonschema
Requires-Dist: mmh3
Requires-Dist: numpy <1.25,>=1.22
Requires-Dist: pandas <3,>=1.4.3
Requires-Dist: protobuf <5.0.0,>=4.24.0
Requires-Dist: pyarrow >=4
Requires-Dist: pydantic >=2.0.0
Requires-Dist: pygments <3,>=2.12.0
Requires-Dist: PyYAML <7,>=5.4.0
Requires-Dist: requests
Requires-Dist: SQLAlchemy[mypy] >1
Requires-Dist: tabulate <1,>=0.8.0
Requires-Dist: tenacity <9,>=7
Requires-Dist: toml <1,>=0.10.0
Requires-Dist: tqdm <5,>=4
Requires-Dist: typeguard >=4.0.0
Requires-Dist: fastapi >=0.68.0
Requires-Dist: uvicorn[standard] <1,>=0.14.0
Requires-Dist: dask ==2024.6.2
Requires-Dist: bowler
Requires-Dist: httpx >=0.23.3
Requires-Dist: importlib-resources <7,>=6.0.0
Requires-Dist: importlib-metadata <7,>=6.8.0
Requires-Dist: gunicorn ; platform_system != "Windows"
Provides-Extra: aws
Requires-Dist: boto3 <2,>=1.17.0 ; extra == 'aws'
Requires-Dist: docker >=5.0.2 ; extra == 'aws'
Requires-Dist: fsspec <=2024.1.0 ; extra == 'aws'
Provides-Extra: azure
Requires-Dist: azure-storage-blob >=0.37.0 ; extra == 'azure'
Requires-Dist: azure-identity >=1.6.1 ; extra == 'azure'
Requires-Dist: SQLAlchemy >=1.4.19 ; extra == 'azure'
Requires-Dist: pyodbc >=4.0.30 ; extra == 'azure'
Requires-Dist: pymssql ; extra == 'azure'
Provides-Extra: bytewax
Requires-Dist: bytewax ==0.15.1 ; extra == 'bytewax'
Requires-Dist: docker >=5.0.2 ; extra == 'bytewax'
Requires-Dist: kubernetes <=20.13.0 ; extra == 'bytewax'
Provides-Extra: cassandra
Requires-Dist: cassandra-driver <4,>=3.24.0 ; extra == 'cassandra'
Provides-Extra: ci
Requires-Dist: build ; extra == 'ci'
Requires-Dist: virtualenv ==20.23.0 ; extra == 'ci'
Requires-Dist: cryptography <43,>=35.0 ; extra == 'ci'
Requires-Dist: ruff >=0.3.3 ; extra == 'ci'
Requires-Dist: grpcio-testing <2,>=1.56.2 ; extra == 'ci'
Requires-Dist: httpx >=0.23.3 ; extra == 'ci'
Requires-Dist: minio ==7.1.0 ; extra == 'ci'
Requires-Dist: mock ==2.0.0 ; extra == 'ci'
Requires-Dist: moto <5 ; extra == 'ci'
Requires-Dist: mypy >=1.4.1 ; extra == 'ci'
Requires-Dist: urllib3 <3,>=1.25.4 ; extra == 'ci'
Requires-Dist: psutil ==5.9.0 ; extra == 'ci'
Requires-Dist: py >=1.11.0 ; extra == 'ci'
Requires-Dist: pytest <8,>=6.0.0 ; extra == 'ci'
Requires-Dist: pytest-cov ; extra == 'ci'
Requires-Dist: pytest-xdist ; extra == 'ci'
Requires-Dist: pytest-benchmark <4,>=3.4.1 ; extra == 'ci'
Requires-Dist: pytest-lazy-fixture ==0.6.3 ; extra == 'ci'
Requires-Dist: pytest-timeout ==1.4.2 ; extra == 'ci'
Requires-Dist: pytest-ordering ~=0.6.0 ; extra == 'ci'
Requires-Dist: pytest-mock ==1.10.4 ; extra == 'ci'
Requires-Dist: pytest-env ; extra == 'ci'
Requires-Dist: Sphinx <7,>4.0.0 ; extra == 'ci'
Requires-Dist: testcontainers ==4.3.3 ; extra == 'ci'
Requires-Dist: firebase-admin <6,>=5.2.0 ; extra == 'ci'
Requires-Dist: pre-commit <3.3.2 ; extra == 'ci'
Requires-Dist: assertpy ==1.1 ; extra == 'ci'
Requires-Dist: pip-tools ; extra == 'ci'
Requires-Dist: pybindgen ; extra == 'ci'
Requires-Dist: types-protobuf ~=3.19.22 ; extra == 'ci'
Requires-Dist: types-python-dateutil ; extra == 'ci'
Requires-Dist: types-pytz ; extra == 'ci'
Requires-Dist: types-PyYAML ; extra == 'ci'
Requires-Dist: types-redis ; extra == 'ci'
Requires-Dist: types-requests <2.31.0 ; extra == 'ci'
Requires-Dist: types-setuptools ; extra == 'ci'
Requires-Dist: types-tabulate ; extra == 'ci'
Requires-Dist: virtualenv <20.24.2 ; extra == 'ci'
Requires-Dist: google-api-core <3,>=1.23.0 ; extra == 'ci'
Requires-Dist: googleapis-common-protos <2,>=1.52.0 ; extra == 'ci'
Requires-Dist: google-cloud-bigquery[pandas] <3.13.0,>=2 ; extra == 'ci'
Requires-Dist: google-cloud-bigquery-storage <3,>=2.0.0 ; extra == 'ci'
Requires-Dist: google-cloud-datastore <3,>=2.1.0 ; extra == 'ci'
Requires-Dist: google-cloud-storage <3,>=1.34.0 ; extra == 'ci'
Requires-Dist: google-cloud-bigtable <3,>=2.11.0 ; extra == 'ci'
Requires-Dist: fsspec <=2024.1.0 ; extra == 'ci'
Requires-Dist: redis <5,>=4.2.2 ; extra == 'ci'
Requires-Dist: hiredis <3,>=2.0.0 ; extra == 'ci'
Requires-Dist: boto3 <2,>=1.17.0 ; extra == 'ci'
Requires-Dist: docker >=5.0.2 ; extra == 'ci'
Requires-Dist: bytewax ==0.15.1 ; extra == 'ci'
Requires-Dist: kubernetes <=20.13.0 ; extra == 'ci'
Requires-Dist: snowflake-connector-python[pandas] <4,>=3.7 ; extra == 'ci'
Requires-Dist: pyspark <4,>=3.0.0 ; extra == 'ci'
Requires-Dist: psycopg2-binary <3,>=2.8.3 ; extra == 'ci'
Requires-Dist: pymysql ; extra == 'ci'
Requires-Dist: types-PyMySQL ; extra == 'ci'
Requires-Dist: mysql-connector-python ; extra == 'ci'
Requires-Dist: trino <0.400.0,>=0.305.0 ; extra == 'ci'
Requires-Dist: regex ; extra == 'ci'
Requires-Dist: great-expectations >=0.15.41 ; extra == 'ci'
Requires-Dist: happybase <3,>=1.2.0 ; extra == 'ci'
Requires-Dist: cassandra-driver <4,>=3.24.0 ; extra == 'ci'
Requires-Dist: azure-storage-blob >=0.37.0 ; extra == 'ci'
Requires-Dist: azure-identity >=1.6.1 ; extra == 'ci'
Requires-Dist: SQLAlchemy >=1.4.19 ; extra == 'ci'
Requires-Dist: pyodbc >=4.0.30 ; extra == 'ci'
Requires-Dist: pymssql ; extra == 'ci'
Requires-Dist: rockset >=1.0.3 ; extra == 'ci'
Requires-Dist: hazelcast-python-client >=5.1 ; extra == 'ci'
Requires-Dist: ibis-framework ; extra == 'ci'
Requires-Dist: ibis-substrait ; extra == 'ci'
Requires-Dist: grpcio <2,>=1.56.2 ; extra == 'ci'
Requires-Dist: grpcio-tools <2,>=1.56.2 ; extra == 'ci'
Requires-Dist: grpcio-reflection <2,>=1.56.2 ; extra == 'ci'
Requires-Dist: grpcio-health-checking <2,>=1.56.2 ; extra == 'ci'
Requires-Dist: ibis-framework[duckdb] ; extra == 'ci'
Provides-Extra: dev
Requires-Dist: build ; extra == 'dev'
Requires-Dist: virtualenv ==20.23.0 ; extra == 'dev'
Requires-Dist: cryptography <43,>=35.0 ; extra == 'dev'
Requires-Dist: ruff >=0.3.3 ; extra == 'dev'
Requires-Dist: grpcio-testing <2,>=1.56.2 ; extra == 'dev'
Requires-Dist: httpx >=0.23.3 ; extra == 'dev'
Requires-Dist: minio ==7.1.0 ; extra == 'dev'
Requires-Dist: mock ==2.0.0 ; extra == 'dev'
Requires-Dist: moto <5 ; extra == 'dev'
Requires-Dist: mypy >=1.4.1 ; extra == 'dev'
Requires-Dist: urllib3 <3,>=1.25.4 ; extra == 'dev'
Requires-Dist: psutil ==5.9.0 ; extra == 'dev'
Requires-Dist: py >=1.11.0 ; extra == 'dev'
Requires-Dist: pytest <8,>=6.0.0 ; extra == 'dev'
Requires-Dist: pytest-cov ; extra == 'dev'
Requires-Dist: pytest-xdist ; extra == 'dev'
Requires-Dist: pytest-benchmark <4,>=3.4.1 ; extra == 'dev'
Requires-Dist: pytest-lazy-fixture ==0.6.3 ; extra == 'dev'
Requires-Dist: pytest-timeout ==1.4.2 ; extra == 'dev'
Requires-Dist: pytest-ordering ~=0.6.0 ; extra == 'dev'
Requires-Dist: pytest-mock ==1.10.4 ; extra == 'dev'
Requires-Dist: pytest-env ; extra == 'dev'
Requires-Dist: Sphinx <7,>4.0.0 ; extra == 'dev'
Requires-Dist: testcontainers ==4.3.3 ; extra == 'dev'
Requires-Dist: firebase-admin <6,>=5.2.0 ; extra == 'dev'
Requires-Dist: pre-commit <3.3.2 ; extra == 'dev'
Requires-Dist: assertpy ==1.1 ; extra == 'dev'
Requires-Dist: pip-tools ; extra == 'dev'
Requires-Dist: pybindgen ; extra == 'dev'
Requires-Dist: types-protobuf ~=3.19.22 ; extra == 'dev'
Requires-Dist: types-python-dateutil ; extra == 'dev'
Requires-Dist: types-pytz ; extra == 'dev'
Requires-Dist: types-PyYAML ; extra == 'dev'
Requires-Dist: types-redis ; extra == 'dev'
Requires-Dist: types-requests <2.31.0 ; extra == 'dev'
Requires-Dist: types-setuptools ; extra == 'dev'
Requires-Dist: types-tabulate ; extra == 'dev'
Requires-Dist: virtualenv <20.24.2 ; extra == 'dev'
Requires-Dist: google-api-core <3,>=1.23.0 ; extra == 'dev'
Requires-Dist: googleapis-common-protos <2,>=1.52.0 ; extra == 'dev'
Requires-Dist: google-cloud-bigquery[pandas] <3.13.0,>=2 ; extra == 'dev'
Requires-Dist: google-cloud-bigquery-storage <3,>=2.0.0 ; extra == 'dev'
Requires-Dist: google-cloud-datastore <3,>=2.1.0 ; extra == 'dev'
Requires-Dist: google-cloud-storage <3,>=1.34.0 ; extra == 'dev'
Requires-Dist: google-cloud-bigtable <3,>=2.11.0 ; extra == 'dev'
Requires-Dist: fsspec <=2024.1.0 ; extra == 'dev'
Requires-Dist: redis <5,>=4.2.2 ; extra == 'dev'
Requires-Dist: hiredis <3,>=2.0.0 ; extra == 'dev'
Requires-Dist: boto3 <2,>=1.17.0 ; extra == 'dev'
Requires-Dist: docker >=5.0.2 ; extra == 'dev'
Requires-Dist: bytewax ==0.15.1 ; extra == 'dev'
Requires-Dist: kubernetes <=20.13.0 ; extra == 'dev'
Requires-Dist: snowflake-connector-python[pandas] <4,>=3.7 ; extra == 'dev'
Requires-Dist: pyspark <4,>=3.0.0 ; extra == 'dev'
Requires-Dist: psycopg2-binary <3,>=2.8.3 ; extra == 'dev'
Requires-Dist: pymysql ; extra == 'dev'
Requires-Dist: types-PyMySQL ; extra == 'dev'
Requires-Dist: mysql-connector-python ; extra == 'dev'
Requires-Dist: trino <0.400.0,>=0.305.0 ; extra == 'dev'
Requires-Dist: regex ; extra == 'dev'
Requires-Dist: great-expectations >=0.15.41 ; extra == 'dev'
Requires-Dist: happybase <3,>=1.2.0 ; extra == 'dev'
Requires-Dist: cassandra-driver <4,>=3.24.0 ; extra == 'dev'
Requires-Dist: azure-storage-blob >=0.37.0 ; extra == 'dev'
Requires-Dist: azure-identity >=1.6.1 ; extra == 'dev'
Requires-Dist: SQLAlchemy >=1.4.19 ; extra == 'dev'
Requires-Dist: pyodbc >=4.0.30 ; extra == 'dev'
Requires-Dist: pymssql ; extra == 'dev'
Requires-Dist: rockset >=1.0.3 ; extra == 'dev'
Requires-Dist: hazelcast-python-client >=5.1 ; extra == 'dev'
Requires-Dist: ibis-framework ; extra == 'dev'
Requires-Dist: ibis-substrait ; extra == 'dev'
Requires-Dist: grpcio <2,>=1.56.2 ; extra == 'dev'
Requires-Dist: grpcio-tools <2,>=1.56.2 ; extra == 'dev'
Requires-Dist: grpcio-reflection <2,>=1.56.2 ; extra == 'dev'
Requires-Dist: grpcio-health-checking <2,>=1.56.2 ; extra == 'dev'
Requires-Dist: ibis-framework[duckdb] ; extra == 'dev'
Provides-Extra: docs
Requires-Dist: build ; extra == 'docs'
Requires-Dist: virtualenv ==20.23.0 ; extra == 'docs'
Requires-Dist: cryptography <43,>=35.0 ; extra == 'docs'
Requires-Dist: ruff >=0.3.3 ; extra == 'docs'
Requires-Dist: grpcio-testing <2,>=1.56.2 ; extra == 'docs'
Requires-Dist: httpx >=0.23.3 ; extra == 'docs'
Requires-Dist: minio ==7.1.0 ; extra == 'docs'
Requires-Dist: mock ==2.0.0 ; extra == 'docs'
Requires-Dist: moto <5 ; extra == 'docs'
Requires-Dist: mypy >=1.4.1 ; extra == 'docs'
Requires-Dist: urllib3 <3,>=1.25.4 ; extra == 'docs'
Requires-Dist: psutil ==5.9.0 ; extra == 'docs'
Requires-Dist: py >=1.11.0 ; extra == 'docs'
Requires-Dist: pytest <8,>=6.0.0 ; extra == 'docs'
Requires-Dist: pytest-cov ; extra == 'docs'
Requires-Dist: pytest-xdist ; extra == 'docs'
Requires-Dist: pytest-benchmark <4,>=3.4.1 ; extra == 'docs'
Requires-Dist: pytest-lazy-fixture ==0.6.3 ; extra == 'docs'
Requires-Dist: pytest-timeout ==1.4.2 ; extra == 'docs'
Requires-Dist: pytest-ordering ~=0.6.0 ; extra == 'docs'
Requires-Dist: pytest-mock ==1.10.4 ; extra == 'docs'
Requires-Dist: pytest-env ; extra == 'docs'
Requires-Dist: Sphinx <7,>4.0.0 ; extra == 'docs'
Requires-Dist: testcontainers ==4.3.3 ; extra == 'docs'
Requires-Dist: firebase-admin <6,>=5.2.0 ; extra == 'docs'
Requires-Dist: pre-commit <3.3.2 ; extra == 'docs'
Requires-Dist: assertpy ==1.1 ; extra == 'docs'
Requires-Dist: pip-tools ; extra == 'docs'
Requires-Dist: pybindgen ; extra == 'docs'
Requires-Dist: types-protobuf ~=3.19.22 ; extra == 'docs'
Requires-Dist: types-python-dateutil ; extra == 'docs'
Requires-Dist: types-pytz ; extra == 'docs'
Requires-Dist: types-PyYAML ; extra == 'docs'
Requires-Dist: types-redis ; extra == 'docs'
Requires-Dist: types-requests <2.31.0 ; extra == 'docs'
Requires-Dist: types-setuptools ; extra == 'docs'
Requires-Dist: types-tabulate ; extra == 'docs'
Requires-Dist: virtualenv <20.24.2 ; extra == 'docs'
Requires-Dist: google-api-core <3,>=1.23.0 ; extra == 'docs'
Requires-Dist: googleapis-common-protos <2,>=1.52.0 ; extra == 'docs'
Requires-Dist: google-cloud-bigquery[pandas] <3.13.0,>=2 ; extra == 'docs'
Requires-Dist: google-cloud-bigquery-storage <3,>=2.0.0 ; extra == 'docs'
Requires-Dist: google-cloud-datastore <3,>=2.1.0 ; extra == 'docs'
Requires-Dist: google-cloud-storage <3,>=1.34.0 ; extra == 'docs'
Requires-Dist: google-cloud-bigtable <3,>=2.11.0 ; extra == 'docs'
Requires-Dist: fsspec <=2024.1.0 ; extra == 'docs'
Requires-Dist: redis <5,>=4.2.2 ; extra == 'docs'
Requires-Dist: hiredis <3,>=2.0.0 ; extra == 'docs'
Requires-Dist: boto3 <2,>=1.17.0 ; extra == 'docs'
Requires-Dist: docker >=5.0.2 ; extra == 'docs'
Requires-Dist: bytewax ==0.15.1 ; extra == 'docs'
Requires-Dist: kubernetes <=20.13.0 ; extra == 'docs'
Requires-Dist: snowflake-connector-python[pandas] <4,>=3.7 ; extra == 'docs'
Requires-Dist: pyspark <4,>=3.0.0 ; extra == 'docs'
Requires-Dist: psycopg2-binary <3,>=2.8.3 ; extra == 'docs'
Requires-Dist: pymysql ; extra == 'docs'
Requires-Dist: types-PyMySQL ; extra == 'docs'
Requires-Dist: mysql-connector-python ; extra == 'docs'
Requires-Dist: trino <0.400.0,>=0.305.0 ; extra == 'docs'
Requires-Dist: regex ; extra == 'docs'
Requires-Dist: great-expectations >=0.15.41 ; extra == 'docs'
Requires-Dist: happybase <3,>=1.2.0 ; extra == 'docs'
Requires-Dist: cassandra-driver <4,>=3.24.0 ; extra == 'docs'
Requires-Dist: azure-storage-blob >=0.37.0 ; extra == 'docs'
Requires-Dist: azure-identity >=1.6.1 ; extra == 'docs'
Requires-Dist: SQLAlchemy >=1.4.19 ; extra == 'docs'
Requires-Dist: pyodbc >=4.0.30 ; extra == 'docs'
Requires-Dist: pymssql ; extra == 'docs'
Requires-Dist: rockset >=1.0.3 ; extra == 'docs'
Requires-Dist: hazelcast-python-client >=5.1 ; extra == 'docs'
Requires-Dist: ibis-framework ; extra == 'docs'
Requires-Dist: ibis-substrait ; extra == 'docs'
Requires-Dist: grpcio <2,>=1.56.2 ; extra == 'docs'
Requires-Dist: grpcio-tools <2,>=1.56.2 ; extra == 'docs'
Requires-Dist: grpcio-reflection <2,>=1.56.2 ; extra == 'docs'
Requires-Dist: grpcio-health-checking <2,>=1.56.2 ; extra == 'docs'
Requires-Dist: ibis-framework[duckdb] ; extra == 'docs'
Provides-Extra: duckdb
Requires-Dist: ibis-framework[duckdb] ; extra == 'duckdb'
Provides-Extra: gcp
Requires-Dist: google-api-core <3,>=1.23.0 ; extra == 'gcp'
Requires-Dist: googleapis-common-protos <2,>=1.52.0 ; extra == 'gcp'
Requires-Dist: google-cloud-bigquery[pandas] <3.13.0,>=2 ; extra == 'gcp'
Requires-Dist: google-cloud-bigquery-storage <3,>=2.0.0 ; extra == 'gcp'
Requires-Dist: google-cloud-datastore <3,>=2.1.0 ; extra == 'gcp'
Requires-Dist: google-cloud-storage <3,>=1.34.0 ; extra == 'gcp'
Requires-Dist: google-cloud-bigtable <3,>=2.11.0 ; extra == 'gcp'
Requires-Dist: fsspec <=2024.1.0 ; extra == 'gcp'
Provides-Extra: ge
Requires-Dist: great-expectations >=0.15.41 ; extra == 'ge'
Provides-Extra: grpcio
Requires-Dist: grpcio <2,>=1.56.2 ; extra == 'grpcio'
Requires-Dist: grpcio-tools <2,>=1.56.2 ; extra == 'grpcio'
Requires-Dist: grpcio-reflection <2,>=1.56.2 ; extra == 'grpcio'
Requires-Dist: grpcio-health-checking <2,>=1.56.2 ; extra == 'grpcio'
Provides-Extra: hazelcast
Requires-Dist: hazelcast-python-client >=5.1 ; extra == 'hazelcast'
Provides-Extra: hbase
Requires-Dist: happybase <3,>=1.2.0 ; extra == 'hbase'
Provides-Extra: ibis
Requires-Dist: ibis-framework ; extra == 'ibis'
Requires-Dist: ibis-substrait ; extra == 'ibis'
Provides-Extra: k8s
Requires-Dist: kubernetes <=20.13.0 ; extra == 'k8s'
Provides-Extra: mysql
Requires-Dist: pymysql ; extra == 'mysql'
Requires-Dist: types-PyMySQL ; extra == 'mysql'
Requires-Dist: mysql-connector-python ; extra == 'mysql'
Provides-Extra: postgres
Requires-Dist: psycopg2-binary <3,>=2.8.3 ; extra == 'postgres'
Provides-Extra: redis
Requires-Dist: redis <5,>=4.2.2 ; extra == 'redis'
Requires-Dist: hiredis <3,>=2.0.0 ; extra == 'redis'
Provides-Extra: rockset
Requires-Dist: rockset >=1.0.3 ; extra == 'rockset'
Provides-Extra: snowflake
Requires-Dist: snowflake-connector-python[pandas] <4,>=3.7 ; extra == 'snowflake'
Provides-Extra: spark
Requires-Dist: pyspark <4,>=3.0.0 ; extra == 'spark'
Provides-Extra: trino
Requires-Dist: trino <0.400.0,>=0.305.0 ; extra == 'trino'
Requires-Dist: regex ; extra == 'trino'
